CHANGELOG.md
datim.py
datimc.py
datimc.cpython-38-x86_64-linux-gnu.so
datim-2.0.1.dist-info/entry_points.txt
datim-2.0.1.dist-info/WHEEL
datim-2.0.1.dist-info/METADATA
datim-2.0.1.dist-info/RECORD
