Metadata-Version: 2.1
Name: datim
Version: 2.0.1
Summary: Data as an image.
Home-page: https://github.com/markjoshwel/datim
License: Unlicense
Author: Your Name
Author-email: you@example.com
Requires-Python: >=3.6.2,<4.0.0
Classifier: License :: Other/Proprietary License
Classifier: Programming Language :: Python :: 3
Classifier: Programming Language :: Python :: 3.10
Classifier: Programming Language :: Python :: 3.7
Classifier: Programming Language :: Python :: 3.8
Classifier: Programming Language :: Python :: 3.9
Provides-Extra: optional
Requires-Dist: Pillow (>=8.3.2,<9.0.0)
Requires-Dist: lz4 (>=3.1.3,<4.0.0)
Requires-Dist: tqdm (>=4.62.3,<5.0.0); extra == "optional"
Project-URL: Repository, https://github.com/markjoshwel/datim
